zhukovmisha2/__init__.py
zhukovmisha2/add.py
zhukovmisha2/subtract.py
zhukovmisha2/extras/__init__.py
zhukovmisha2/extras/divide.py
zhukovmisha2/extras/multiply.py
zhukovmisha2-0.0.1.dist-info/METADATA
zhukovmisha2-0.0.1.dist-info/WHEEL
zhukovmisha2-0.0.1.dist-info/top_level.txt
zhukovmisha2-0.0.1.dist-info/RECORD
